{
    "url": "https://www.gutenberg.org/ebooks/32832",
    "autor": "Dick, Philip K., 1928-1982",
    "titulo": "Piper in the Woods",
    "publicacao": "United States: Greenleaf Publishing Company,1954.",
    "resumo": "\"Piper in the Woods\" by Philip K. Dick is a science fiction short story written in the early to mid-20th century. The narrative explores themes of identity, purpose, and the psychological consequences of a modern, mechanized society as it contrasts these with the natural world. In the story, a phenomenon is unfolding on Asteroid Y-3, where personnel from Earth are inexplicably developing a belief that they are transforming into plants.  The plot follows Doctor Henry Harris as he investigates a series of bizarre cases where garrison personnel report feeling like plants, desiring nothing more than to bask in the sun rather than fulfill their duties. As Harris delves deeper, he learns of a collective psychological phenomenon among the crew, tied to their disillusionment with the rigors of their roles in a technologically advanced society. This leads to the revelation of \"the Pipers,\" a symbolic manifestation of their suppressed desires for a simpler, carefree existence. The story culminates in an understanding that the Pipers are not outside forces but rather a reflection of the men's own psyche grappling with the conflict between duty and the longing to escape into nature. Harris resolves to help them confront these inner conflicts through psychotherapy, aiming to reintegrate them back into their roles while reconciling their yearning for freedom and tranquility. (This is an automatically generated summary.)",
    "idioma": "English",
    "temas": [
        "Science fiction",
        "Short stories",
        "Psychological fiction",
        "Human-alien encounters -- Fiction"
    ]
}