{
    "url": "https://www.gutenberg.org/ebooks/15481",
    "autor": "Various",
    "titulo": "Chambers's Edinburgh Journal, No. 423Volume 17, New Series, February 7, 1852",
    "publicacao": "United States: Greenleaf Publishing Company,1954.",
    "resumo": "\"Chambers's Edinburgh Journal, No. 423\" by Various is a collection of articles and narratives written during the mid-19th century. This edition features a range of topics, including personal accounts of travels along the Indus River, insights into the daily lives of travelers and natives, and reflections on culture and nature. The aim is to engage the readers with narratives that combine travelogue with social commentary amid a backdrop of literary enlightenment typical of that era.  At the start of the journal, a soldier shares his travel experiences as he journeys from Kurâchee to Sukkur to join a military siege. He vividly describes the circumstances of his journey, including his preparations for the voyage, the characters aboard the steamship, and the various passengers he encounters. Through his observations, readers are introduced to the diverse cultures along the Indus River, enriched with humor and human interaction, while also providing insight into the challenges faced during their travels. The narrative sets an engaging tone that blends adventure with a keen observational eye, making it an enlightening read for those interested in historical travel accounts. (This is an automatically generated summary.)",
    "idioma": "English",
    "temas": [
        "Periodicals"
    ]
}