{
    "url": "https://www.gutenberg.org/ebooks/11347",
    "autor": "Various",
    "titulo": "The Mirror of Literature, Amusement, and Instruction. Volume 13, No. 370, May 16, 1829",
    "publicacao": "United States: Greenleaf Publishing Company,1954.",
    "resumo": "\"The Mirror of Literature, Amusement, and Instruction. Volume 13, No. 370, May…\" is a periodical publication that falls under the category of literary magazine, likely written during the early 19th century, specifically in the late Regency era. This magazine features a blend of literature, commentary, and informative articles, aimed at both entertaining and educating its readers about various subjects, including notable historical events, poetry, and cultural commentary.  The content within this particular volume includes various pieces such as articles on the residence of the young Queen of Portugal and her temporary stay at Laleham Park, lines reflecting on the island of Iona, and poetic dialogues personifying light and dark. Additionally, the magazine features a discussion about the famous literary figure Dr. Samuel Johnson and examines the notion of \"good and evil days\" from a historical and cultural perspective. This volume serves as a snapshot of the social and literary consciousness of its time, blending historical accounts with artistic interpretations and thoughtful commentary. (This is an automatically generated summary.)",
    "idioma": "English",
    "temas": [
        "Popular literature -- Great Britain -- Periodicals"
    ]
}