{
    "url": "https://www.gutenberg.org/ebooks/64143",
    "autor": "Runnels, M. T. (Moses Thurston), 1830-1902",
    "titulo": "Soil and Water Pollution : Presented to the American Public Health Association at New Orleans, Dec. 1880",
    "publicacao": "United States: Greenleaf Publishing Company,1954.",
    "resumo": "\"Soil and Water Pollution: Presented to the American Public Health Association…\" by Moses T. Runnels, M.D. is a scientific publication likely written in the late 19th century. This work addresses critical health concerns regarding soil and water pollution and their detrimental effects on public health. Runnels presents compelling evidence and statistics to articulate how preventable environmental factors contribute significantly to disease and mortality.  In this publication, Runnels meticulously investigates the correlation between environmental cleanliness and health outcomes in Indianapolis, showcasing how polluted soil and water serve as breeding grounds for various diseases, such as typhoid fever and dysentery. He meticulously details observations from wells, privy vaults, and cesspools, providing alarming data on water contamination that poses severe health risks to the community. Ultimately, Runnels advocates for improved sanitary practices and governmental action to remedy these issues, emphasizing the need for robust public health initiatives to stem the tide of preventable diseases exacerbated by poor sanitation conditions. (This is an automatically generated summary.)",
    "idioma": "English",
    "temas": [
        "Water -- Pollution",
        "Water-supply -- Indiana -- Indianapolis"
    ]
}