{
    "url": "https://www.gutenberg.org/ebooks/67560",
    "autor": "Pratt, Ella Farman, 1837-1907",
    "titulo": "All the World Over: Interesting Stories of Travel, Thrilling Adventure and Home Life",
    "publicacao": "United States: Greenleaf Publishing Company,1954.",
    "resumo": "\"All the World Over: Interesting Stories of Travel, Thrilling Adventure and Home...\" by Ella Farman, Mrs. Lucia Chase Bell, Frank H. Converse, and Louise Stockton is a collection of travel narratives and short stories written in the late 19th century. The book offers a journey through various locales, exploring cultural nuances, adventures, and everyday life, with each story presenting unique characters and settings that reflect the authors' experiences.   The opening of the narrative vividly portrays aspects of life in Spain, focusing on the muscular beggars in Spanish cities and the lively culture of dance and music prevalent among the locals. The author paints a lively scene, describing the daily routines of both the beggars and the hardworking population, creating a glimpse into the streets filled with vibrant life. From the unique customs of water-carriers to the bustling markets where colorful fruits and festive items are sold, the narrative captures the essence of Spanish life. The detailed observations of lifestyle, attire, and social customs provide readers with a rich tapestry of the Spanish experience that serves as a portal into the past. (This is an automatically generated summary.)",
    "idioma": "English",
    "temas": [
        "Children's literature",
        "Children's poetry",
        "Children's stories",
        "Voyages and travels -- Juvenile literature",
        "Adventure and adventurers -- Juvenile literature",
        "Families -- Juvenile literature"
    ]
}