{
    "url": "https://www.gutenberg.org/ebooks/70198",
    "autor": "Dehan, Richard, 1863-1932",
    "titulo": "Seven Xmas Eves :  Being the romance of a social evolution",
    "publicacao": "United States: Greenleaf Publishing Company,1954.",
    "resumo": "\"Seven Xmas Eves: Being the Romance of a Social Evolution\" by Richard Dehan et al. is a collection of narratives written in the late 19th century. This work intertwines various stories that explore social themes, with a focus on the lives of impoverished children and the impact of kindness during the Christmas season. The opening chapter introduces Mary Cheevers, a washerwoman who recounts her experiences observing two destitute children, Nick and Nan, highlighting themes of love, innocence, and the harsh realities of life.  The beginning of \"Seven Xmas Eves\" sets the tone for the heartwarming yet somber narratives that follow. Mary Cheevers' testimony reveals her compassion for Nick and Nan, two young children living in dire circumstances, as she follows their struggles and dreams. Mary reflects on her own life while seeking to help these unfortunate souls, emphasizing their innocence and the societal challenges they face. Through her perspective, readers are drawn into the children's plight, establishing an emotional connection as the story unfolds, thus paving the way for the subsequent tales of social evolution during the Christmas period. (This is an automatically generated summary.)",
    "idioma": "English",
    "temas": [
        "Christmas stories"
    ]
}