{
    "url": "https://www.gutenberg.org/ebooks/27922",
    "autor": "Ormondroyd, Edward, 1925-",
    "titulo": "David and the Phoenix",
    "publicacao": "United States: Greenleaf Publishing Company,1954.",
    "resumo": "\"David and the Phoenix\" by Edward Ormondroyd is a children's fantasy novel written in the mid-20th century. The story introduces a young boy named David who embarks on an adventurous journey after moving to a new home where he discovers a majestic mountain. In an unexpected turn of events, he encounters a magical creature—a Phoenix—who becomes an integral part of his exploration and growth, promising to educate him about wonders beyond the ordinary.  At the start of the book, David is captivated by the sight of the mountain near his new home and yearns to climb it. As he helps his family unpack, his excitement builds for the next day’s climb. On his ascent, he experiences the thrill of exploration and stumbles upon the mysterious voice of the Phoenix, who is humorously studying Spanish verbs. This encounter leads David into a world of magic and adventure, filled with intriguing characters and moments that promise exciting escapades as he forms a unique bond with the Phoenix. The opening sets the stage for David’s transformation from an ordinary boy to an adventurer, enriched by the wisdom and fun that the Phoenix has to offer. (This is an automatically generated summary.)",
    "idioma": "English",
    "temas": [
        "Fantasy literature",
        "Humorous stories",
        "Adventure and adventurers -- Fiction",
        "Phoenix (Mythical bird) -- Fiction"
    ]
}