{
    "url": "https://www.gutenberg.org/ebooks/64279",
    "autor": "Garson, Bill, 1917-2000",
    "titulo": "Test For the Pearl",
    "publicacao": "United States: Greenleaf Publishing Company,1954.",
    "resumo": "\"Test For the Pearl\" by Vaseleos Garson is a science fiction novel likely written in the mid-20th century, drawing readers into a vibrant, imaginative universe. The story unfolds on Venus, where the main character, Jarl Gare, a cunning Earthman, aims to secure a rare and precious Venusian pearl to gain his freedom. The book explores themes of survival, adventure, and the struggle against alien foes in a richly described extraterrestrial setting.  The narrative follows Jarl Gare and his formidable companion, Waltk, a Jovian, as they escape from a harsh prison known as \"The Hole.\" The duo navigates the treacherous Venusian jungle in search of the legendary pearl-beds while contending with the hidden dangers posed by the planet's native Chameleon men. As they approach their goal, Gare's cunning and Waltk's brute strength are put to the ultimate test. However, Gare ultimately faces a perilous challenge when the final test of retrieving the pearl proves daunting, highlighting his inherent weakness: color-blindness, which complicates his quest in a dramatic twist. (This is an automatically generated summary.)",
    "idioma": "English",
    "temas": [
        "Science fiction",
        "Short stories",
        "Adventure stories",
        "Venus (Planet) -- Fiction",
        "Escaped prisoners -- Fiction",
        "Treasure hunting -- Fiction"
    ]
}