{
    "url": "https://www.gutenberg.org/ebooks/27567",
    "autor": "Alcott, Louisa May, 1832-1888",
    "titulo": "Aunt Jo's Scrap Bag, Volume 6An Old-Fashioned Thanksgiving, Etc.",
    "publicacao": "United States: Greenleaf Publishing Company,1954.",
    "resumo": "\"Aunt Jo's Scrap Bag, Volume 6\" by Louisa May Alcott is a collection of short stories written in the late 19th century. This volume features various narratives, including themes of family life, adventure, and the innocence of childhood, showcasing Alcott's ability to capture the essence of her characters' experiences. The stories often resonate with readers through their relatable depictions of trials, joys, and whimsical occurrences.  The opening portion of the collection introduces the story \"An Old-Fashioned Thanksgiving,\" where we meet the Bassett family preparing for their Thanksgiving meal on their New Hampshire farm. The narrative paints a warm and inviting picture of rural life, underscored by the bustle of family members engaged in festive preparations. However, the atmosphere is disrupted when Mrs. Bassett receives distressing news about her ailing mother, leading to hurried arrangements and expressions of concern among the children. This sets the stage for themes of adversity and familial bonds, as the characters must navigate both the anticipation of their holiday and the worry for their loved one, showcasing Alcott's deft storytelling from the very outset. (This is an automatically generated summary.)",
    "idioma": "English",
    "temas": [
        "Children's stories"
    ]
}