{
    "url": "https://www.gutenberg.org/ebooks/25988",
    "autor": "Schack, Adolf Friedrich von, 1815-1894",
    "titulo": "Historia de la literatura y del arte dramático en España, tomo II",
    "publicacao": "United States: Greenleaf Publishing Company,1954.",
    "resumo": "\"Historia de la literatura y del arte dramático en España, tomo II\" by Adolfo Federico Conde de Schack is a historical account written in the late 19th century. This work delves into the evolution of Spanish literature and drama, focusing particularly on significant figures and periods in its development, such as Cervantes and the Golden Age of Spanish theater. Readers interested in literary history and the cultural context of Spain will find the discussions engaging and insightful.  The opening of this volume provides a detailed examination of Miguel de Cervantes' life and works, highlighting his contributions to drama after his experiences as a captive in Algiers. It explores Cervantes’ early influences and writings, setting the stage for further discussions on the dramatic landscape of Spain during his time as well as his critical perspective on the theatrical practices of his contemporaries. This portrayal not only contextualizes Cervantes within the larger framework of Spanish literature but also signifies his attempts to carve out a unique identity in a rapidly evolving dramatic tradition. (This is an automatically generated summary.)",
    "idioma": "Spanish",
    "temas": [
        "Spanish drama -- History and criticism"
    ]
}