{
    "url": "https://www.gutenberg.org/ebooks/44462",
    "autor": "Bennett, R. A. R. (Reginald Arthur Renaud), 1866-1930",
    "titulo": "How to Make Electrical MachinesContaining Full Directions for Making Electrical Machines, Induction Coils, Dynamos, and Many Novel Toys to Be Worked by Electricity",
    "publicacao": "United States: Greenleaf Publishing Company,1954.",
    "resumo": "\"How to Make Electrical Machines\" by R. A. R. Bennett is a scientific publication written in the late 19th century. This text serves as a comprehensive guide for readers interested in constructing various electrical devices, including machines and toys that operate on electrical principles. The book aims to impart practical knowledge to amateur electricians, providing detailed instructions and diagrams for building different apparatuses.  The opening of the text introduces readers to the basic construction of an electrical machine, explaining materials, measurements, and assembly steps. Bennett emphasizes the importance of ensuring the machine functions correctly, outlining the necessary precautions, such as avoiding damp air and properly heating components before use. Detailed instructions are given for crafting parts like frames, glass plates, and conductors, demonstrating the author's commitment to accessible hands-on learning in the field of electricity. Overall, the beginning of this work sets the stage for an engaging exploration of electrical engineering as both an educational and recreational pursuit. (This is an automatically generated summary.)",
    "idioma": "English",
    "temas": [
        "Electric apparatus and appliances",
        "Electric apparatus and appliances -- Amateurs' manuals",
        "Electricity -- Handbooks, manuals, etc.",
        "Electric motors"
    ]
}