{
    "url": "https://www.gutenberg.org/ebooks/19242",
    "autor": "Baha'i World Centre",
    "titulo": "Bahíyyih Khánum",
    "publicacao": "United States: Greenleaf Publishing Company,1954.",
    "resumo": "\"Bahíyyih Khánum\" by the Baha'i World Centre is a historical account likely written in the late 19th century. This work is dedicated to the life and legacy of Bahíyyih Khánum, also known as the Greatest Holy Leaf, who was a significant female figure in the Bahá'í Faith and the daughter of Bahá'u'lláh. The book explores her spiritual contributions, trials, and profound impact on the Bahá'í community, providing readers with an insight into her revered position within the faith.  The opening of the book reveals a dedicatory passage that acknowledges the profound spiritual legacy of Bahíyyih Khánum. Through luminous language, it emphasizes her divine qualities, her closeness to both her father Bahá'u'lláh and her brother 'Abdu'l-Bahá, and her unwavering faith amidst trials. The first section also includes direct references to prayers and messages written in her honor, expressing deep love and appreciation for her sacrifice and service within the Bahá'í community. This initial portion sets a reverent tone, presenting Bahíyyih Khánum as a central figure whose life and contributions resonate deeply within the teachings of the Bahá'í Faith. (This is an automatically generated summary.)",
    "idioma": "English",
    "temas": [
        "Bahai Faith",
        "Bahíyyih, Khánum",
        "Bahíyyih, Khánum -- Correspondence"
    ]
}