{
    "url": "https://www.gutenberg.org/ebooks/46330",
    "autor": "Hegel, Georg Wilhelm Friedrich, 1770-1831",
    "titulo": "The Introduction to Hegel's Philosophy of Fine ArtsTranslated from the German with Notes and Prefatory Essay",
    "publicacao": "United States: Greenleaf Publishing Company,1954.",
    "resumo": "\"The Introduction to Hegel's Philosophy of Fine Art\" by Hegel is a philosophical publication written in the late 19th century. The book serves as an exposition of Hegel's ideas surrounding art and aesthetics, laying a foundation for understanding how beauty and artistic expression can be analyzed philosophically. It explores the intersection of art with human experience, culture, and historical context, seeking to establish a systematized understanding of artistic beauty.  The opening of the text introduces the reader to the concept of aesthetics and its significance in understanding art, distinguishing it from natural beauty and emphasizing the philosophical treatment of fine art. Hegel explains the limitations and misconceptions surrounding artistic beauty while defending the need for a scientific approach to art. He critiques prevailing notions regarding the nature of art, discussing the role of human activity in artistic creation and addressing the complex relationship between artistic talent and structured rules. This introductory portion sets the stage for a deeper exploration of the principles underlying art and beauty as central themes in Hegel's philosophy. (This is an automatically generated summary.)",
    "idioma": "English",
    "temas": [
        "Aesthetics",
        "Art -- Philosophy"
    ]
}