{
    "url": "https://www.gutenberg.org/ebooks/63347",
    "autor": "Mackinder, Halford John, 1861-1947",
    "titulo": "Seven Lectures on the United Kingdom for use in IndiaReissued for use in the United Kingdom",
    "publicacao": "United States: Greenleaf Publishing Company,1954.",
    "resumo": "\"Seven Lectures on the United Kingdom for use in India\" by Halford John Mackinder is a collection of educational lectures written in the early 20th century. The work is designed for Indian schoolchildren to provide them with insights into the United Kingdom and its geography, history, and people through visual instruction. The goal is to foster sympathy and understanding among students of the British Empire, highlighting its diverse components.  The opening of the collection establishes the book's purpose and audience, detailing the context in which the lectures were developed by the Visual Instruction Committee, under the Colonial Office. It explains the need for a standardized method of teaching about the different parts of the Empire, especially focusing on the United Kingdom’s significance to India. Mackinder emphasizes the importance of visual aids, such as lantern slides, to convey the concepts effectively. This introduction sets a tone of educational outreach, aiming to bridge the gap between diverse cultures within the Empire by promoting a shared understanding of geography and national identity. (This is an automatically generated summary.)",
    "idioma": "English",
    "temas": [
        "Great Britain"
    ]
}